tms_mcp/__init__.py
tms_mcp/config.py
tms_mcp/main.py
tms_mcp/py.typed
tms_mcp/server.py
tms_mcp/custom_logging/logging_config.yaml
tms_mcp/custom_logging/logging_format.py
tms_mcp/docs/basic_info.md
tms_mcp/docs/inavi/endpoints_summary.md
tms_mcp/docs/inavi/openapi.json
tms_mcp/docs/inavi/overviews/coordinates.json
tms_mcp/docs/inavi/overviews/route-distance-matrix.json
tms_mcp/docs/inavi/overviews/route-normal-via.json
tms_mcp/docs/inavi/overviews/route-time.json
tms_mcp/docs/inavi/schemas/request_body/route-distance-matrix.json
tms_mcp/docs/inavi/schemas/request_body/route-normal-via.json
tms_mcp/docs/inavi/schemas/request_body/route-time.json
tms_mcp/docs/inavi/schemas/response/coordinates/200.json
tms_mcp/docs/inavi/schemas/response/route-distance-matrix/200.json
tms_mcp/docs/inavi/schemas/response/route-normal-via/200.json
tms_mcp/docs/inavi/schemas/response/route-time/200.json
tms_mcp/docs/integration_patterns/agentic_coding_guidelines.md
tms_mcp/docs/integration_patterns/list.md
tms_mcp/docs/integration_patterns/last_mile/basic.md
tms_mcp/docs/integration_patterns/last_mile/navigation.md
tms_mcp/docs/omelet/endpoints_summary.md
tms_mcp/docs/omelet/openapi.json
tms_mcp/docs/omelet/examples/request_body/advanced-vrp/AdvancedVRPExample.json
tms_mcp/docs/omelet/examples/request_body/advanced-vrp-long/AdvancedVRPExample.json
tms_mcp/docs/omelet/examples/request_body/cost-matrix/CostMatrixBasicExample.json
tms_mcp/docs/omelet/examples/request_body/cost-matrix/CostMatrixDistanceOnly.json
tms_mcp/docs/omelet/examples/request_body/fsmvrp/FSMVRPExample.json
tms_mcp/docs/omelet/examples/request_body/fsmvrp-long/FSMVRPExample.json
tms_mcp/docs/omelet/examples/request_body/pdp/PDPBasicExample.json
tms_mcp/docs/omelet/examples/request_body/pdp/PDPExample.json
tms_mcp/docs/omelet/examples/request_body/pdp-long/PDPBasicExample.json
tms_mcp/docs/omelet/examples/request_body/pdp-long/PDPExample.json
tms_mcp/docs/omelet/examples/request_body/vrp/BasicVRPExample.json
tms_mcp-0.5.1.dist-info/licenses/LICENSE
tms_mcp-0.5.1.dist-info/METADATA
tms_mcp-0.5.1.dist-info/WHEEL
tms_mcp-0.5.1.dist-info/entry_points.txt
tms_mcp-0.5.1.dist-info/top_level.txt
tms_mcp-0.5.1.dist-info/RECORD
