Metadata-Version: 2.4
Name: tms-mcp
Version: 0.5.1
Summary: MCP server for exploring Omelet's Routing Engine and iNavi's Maps API to help build a TMS
Author-email: Omelet <dev.shared@omelet.ai>
License-Expression: MIT
Project-URL: Homepage, https://github.com/omelet-ai/tms-dev-mcp
Project-URL: Repository, https://github.com/omelet-ai/tms-dev-mcp.git
Project-URL: Documentation, https://github.com/omelet-ai/tms-dev-mcp#readme
Project-URL: Issues, https://github.com/omelet-ai/tms-dev-mcp/issues
Keywords: mcp,tms,routing,logistics,omelet,inavi,maps,api
Classifier: Development Status :: 4 - Beta
Classifier: Intended Audience :: Developers
Classifier: Programming Language :: Python :: 3
Classifier: Programming Language :: Python :: 3.11
Classifier: Topic :: Software Development :: Libraries :: Python Modules
Classifier: Topic :: Scientific/Engineering :: GIS
Requires-Python: <4,>=3.11
License-File: LICENSE
Requires-Dist: aiofiles>=24.1.0
Requires-Dist: fastmcp>=2.11.0
Requires-Dist: jsonref>=1.1.0
Requires-Dist: jsonschema>=4.23.0
Requires-Dist: python-json-logger>=3.2.1
Requires-Dist: pyyaml>=6.0.2
Dynamic: license-file
